<PAMDataset>
  <PAMRasterBand band="1">
    <Histograms>
      <HistItem>
        <HistMin>0.04827385142445564</HistMin>
        <HistMax>0.5010261635482312</HistMax>
        <BucketCount>1000</BucketCount>
        <IncludeOutOfRange>0</IncludeOutOfRange>
        <Approximate>1</Approximate>
        <HistCounts>1|1|2|2|9|3|3|8|8|4|1|5|7|9|9|11|8|8|6|13|27|58|85|135|141|165|168|188|152|85|69|51|46|27|36|37|50|47|50|40|61|58|71|65|84|83|59|97|95|125|85|133|127|144|137|173|140|202|167|206|193|259|249|356|325|293|364|325|479|390|533|414|565|442|571|545|603|510|641|568|684|604|741|712|587|805|656|825|640|845|727|937|764|929|835|983|835|988|839|1098|1017|868|1005|840|1030|828|1003|808|999|793|888|700|864|684|844|731|793|616|726|750|573|651|523|653|505|627|494|569|474|577|447|539|428|525|396|505|475|342|415|357|431|356|387|323|400|321|393|332|385|295|339|268|355|261|316|302|275|278|252|289|227|268|234|266|223|254|194|259|177|250|176|228|209|174|210|165|208|138|168|140|182|135|176|142|163|139|173|147|166|110|157|149|130|135|115|145|96|138|116|134|97|110|108|132|83|137|97|112|79|124|99|67|79|72|100|68|88|77|83|81|92|67|70|52|67|65|83|72|62|73|50|58|65|73|52|59|34|68|52|59|39|44|36|46|31|44|52|36|47|32|44|44|46|37|45|25|37|34|42|28|40|32|32|34|24|32|17|37|22|32|24|40|16|32|21|29|16|31|24|22|17|22|13|18|23|16|22|18|19|18|25|14|16|15|25|24|14|17|18|16|21|22|18|18|14|19|13|10|18|14|14|14|6|17|11|7|7|13|15|7|11|8|15|8|17|11|7|9|14|8|13|9|11|7|9|4|10|17|10|8|9|11|8|6|10|6|6|7|4|7|4|8|4|3|8|4|6|4|9|8|2|10|6|6|3|4|8|4|5|6|5|6|5|6|5|10|4|7|4|4|5|5|7|2|4|5|4|6|3|2|1|3|3|2|4|3|6|2|4|7|6|3|5|2|6|5|3|2|3|4|2|6|4|6|4|4|2|2|2|6|1|2|1|4|4|4|2|1|3|3|3|4|0|1|2|1|5|3|3|3|5|3|5|4|2|6|3|6|2|3|1|2|1|2|1|3|1|2|4|6|1|4|1|3|1|3|3|0|2|2|3|1|2|1|4|3|0|1|2|2|1|3|1|0|4|3|4|3|1|1|2|3|0|5|1|5|1|1|0|1|2|2|0|1|1|3|2|2|3|0|3|1|1|1|1|1|2|0|2|0|1|0|1|1|2|0|2|1|1|1|5|0|0|2|0|3|0|1|2|0|0|1|0|0|3|3|4|0|1|1|2|1|0|2|1|0|1|0|1|0|0|0|1|0|1|3|1|2|1|0|0|1|4|1|0|1|0|1|2|0|0|1|0|1|3|1|2|0|0|2|1|3|0|0|2|3|0|0|0|0|0|4|1|1|1|1|2|2|2|1|1|0|0|1|2|2|0|3|1|0|2|0|1|0|1|2|2|0|0|0|0|2|1|1|0|0|0|1|0|0|0|0|1|0|0|0|0|0|4|2|1|1|0|1|0|1|0|0|0|0|0|0|0|0|0|1|0|1|0|0|2|0|1|1|0|0|0|0|1|1|0|0|0|1|0|0|2|0|0|0|0|0|1|2|0|0|0|1|0|0|0|0|1|0|0|0|0|1|0|3|0|1|1|0|0|1|0|0|0|0|0|0|0|1|0|0|0|1|0|0|0|0|1|0|1|0|1|0|0|0|0|0|0|0|0|0|0|0|0|0|0|0|0|1|0|0|0|0|0|1|0|0|0|0|0|1|0|0|0|0|0|1|0|0|0|0|0|1|0|0|0|1|0|0|0|0|2|1|0|1|0|0|0|0|0|1|0|0|1|0|0|0|0|0|2|0|0|1|0|0|0|0|0|0|0|0|0|0|0|0|1|0|1|0|0|1|0|0|2|0|0|0|0|0|0|0|0|0|0|1|1|0|0|0|0|0|0|0|0|0|0|0|0|0|0|0|0|0|0|0|0|1|0|0|0|0|0|0|0|0|0|0|0|0|0|0|0|0|0|0|0|0|0|0|0|0|0|0|0|0|0|0|0|0|0|0|0|0|0|0|0|0|0|0|0|0|0|0|0|0|0|0|0|0|0|0|0|0|0|0|0|0|0|0|0|0|0|0|0|0|0|0|0|0|0|0|0|0|0|0|0|0|0|0|0|0|0|0|0|0|0|0|0|0|0|0|0|0|0|0|0|0|0|0|0|0|0|0|0|0|0|0|0|0|0|0|0|0|0|0|0|0|0|0|0|0|0|0|0|0|0|0|0|0|0|0|0|1|0|1</HistCounts>
      </HistItem>
      <HistItem>
        <HistMin>0.06263155270740389</HistMin>
        <HistMax>1.000468449998647</HistMax>
        <BucketCount>1000</BucketCount>
        <IncludeOutOfRange>0</IncludeOutOfRange>
        <Approximate>1</Approximate>
        <HistCounts>85|79|97|90|131|143|148|187|206|254|287|314|400|374|510|673|656|872|923|979|1151|1142|1294|1268|1348|1487|1479|1473|1824|1669|2019|1823|1937|2081|1838|1862|2030|1738|1740|1562|1544|1509|1296|1206|1286|1121|1163|1031|955|1010|874|741|889|720|790|723|700|683|616|618|553|541|542|507|462|502|415|450|385|372|360|313|312|346|312|334|273|278|287|229|255|252|222|253|215|198|187|151|168|177|171|171|119|138|157|127|126|133|91|133|98|80|86|87|95|77|84|86|68|75|77|62|60|55|56|68|48|50|57|39|40|40|35|41|39|36|45|37|38|37|40|34|30|35|28|20|25|21|20|21|22|31|16|22|25|18|10|27|23|20|14|16|11|10|13|9|13|13|10|16|10|11|12|13|7|15|12|11|10|10|9|10|5|4|6|8|8|13|9|5|10|7|6|9|11|6|7|4|4|9|4|7|5|3|2|8|7|8|9|5|12|5|3|3|4|4|9|6|4|5|3|4|3|6|3|3|3|4|5|9|1|4|6|7|2|1|4|1|4|5|3|3|2|3|2|2|0|2|3|3|6|0|2|3|3|1|0|5|5|1|4|2|1|1|1|0|1|4|3|1|4|2|1|2|1|1|3|4|0|3|3|2|3|0|1|4|3|2|5|1|0|5|3|1|2|2|3|1|0|3|1|0|1|0|1|0|0|4|3|1|1|1|0|0|0|1|0|1|2|2|0|0|2|0|1|0|2|0|1|2|0|1|0|1|0|0|1|4|1|0|1|0|0|0|1|0|1|0|1|1|1|0|0|0|0|0|0|0|1|0|0|1|0|0|1|0|0|1|0|1|0|1|0|0|3|1|0|0|1|0|1|0|1|1|1|0|0|0|0|0|1|1|0|1|2|0|0|0|0|1|1|0|0|0|0|0|0|0|0|0|1|0|0|0|0|0|0|0|0|0|0|0|0|0|0|0|0|0|0|0|0|0|0|0|0|0|0|0|0|0|0|0|0|0|0|0|0|0|0|0|0|0|0|0|0|0|0|0|0|0|0|0|0|0|0|0|0|0|0|0|0|0|0|0|0|0|1|1|0|0|0|0|0|0|0|0|0|0|0|0|0|0|0|0|0|0|0|0|0|0|0|0|0|0|0|0|0|0|0|0|0|0|0|0|0|0|0|0|0|0|0|0|0|0|0|0|0|0|0|0|0|0|0|0|0|0|0|0|0|0|0|0|0|0|0|0|0|0|0|0|0|0|0|0|0|0|0|0|0|0|0|0|0|0|0|0|0|0|0|0|0|0|0|0|0|0|0|0|0|0|0|0|0|0|0|0|0|0|0|0|0|0|0|0|0|0|0|0|0|0|0|0|0|0|0|0|0|0|0|0|0|0|0|0|0|0|0|0|0|0|0|0|0|0|0|0|0|0|0|0|0|0|0|0|0|0|0|0|0|0|0|0|0|0|0|0|0|0|0|0|0|0|0|0|0|0|0|0|0|0|0|0|0|0|0|0|0|0|0|0|0|0|0|0|0|0|0|0|0|0|0|0|0|0|0|0|0|0|0|0|0|0|0|0|0|0|0|0|0|0|0|0|0|0|0|0|0|0|0|0|0|0|0|0|0|0|0|0|0|0|0|0|0|0|0|0|0|0|0|0|0|0|0|0|0|0|0|0|0|0|0|0|0|0|0|0|0|0|0|0|0|0|0|0|0|0|0|0|0|0|0|0|0|0|0|0|0|0|0|0|0|0|0|0|0|0|0|0|0|0|0|0|0|0|0|0|0|0|0|0|0|0|0|0|0|0|0|0|0|0|0|0|0|0|0|0|0|0|0|0|0|0|0|0|0|0|0|0|0|0|0|0|0|0|0|0|0|0|0|0|0|0|0|0|0|0|0|0|0|0|0|0|0|0|0|0|0|0|0|0|0|0|0|0|0|0|0|0|0|0|0|0|0|0|0|0|0|0|0|0|0|0|0|0|0|0|0|0|0|0|0|0|0|0|0|0|0|0|0|0|0|0|0|0|0|0|0|0|0|0|0|0|0|0|0|0|0|0|0|0|0|0|0|0|0|0|0|0|0|0|0|0|0|0|0|0|0|0|0|0|0|0|0|0|0|0|0|0|0|0|0|0|0|0|0|0|0|0|0|0|0|0|0|0|0|0|0|0|0|0|0|0|0|0|0|0|0|0|0|0|0|0|0|0|0|0|0|0|0|0|0|0|0|0|0|0|0|0|0|0|0|0|0|0|0|0|0|0|0|0|0|0|0|0|0|0|0|0|0|0</HistCounts>
      </HistItem>
    </Histograms>
    <Metadata>
      <MDI key="STATISTICS_MAXIMUM">0.50080001354218</MDI>
      <MDI key="STATISTICS_MEAN">0.10395522375205</MDI>
      <MDI key="STATISTICS_MINIMUM">0.048500001430511</MDI>
      <MDI key="STATISTICS_STDDEV">0.027661166426241</MDI>
    </Metadata>
  </PAMRasterBand>
</PAMDataset>
